odoo/addons/account_payment_mandate_sale/README.rst
odoo/addons/account_payment_mandate_sale/__init__.py
odoo/addons/account_payment_mandate_sale/__manifest__.py
odoo/addons/account_payment_mandate_sale/i18n/account_banking_mandate_sale.pot
odoo/addons/account_payment_mandate_sale/i18n/account_payment_mandate_sale.pot
odoo/addons/account_payment_mandate_sale/i18n/ca.po
odoo/addons/account_payment_mandate_sale/i18n/ca_ES.po
odoo/addons/account_payment_mandate_sale/i18n/de.po
odoo/addons/account_payment_mandate_sale/i18n/es.po
odoo/addons/account_payment_mandate_sale/i18n/hr.po
odoo/addons/account_payment_mandate_sale/i18n/it.po
odoo/addons/account_payment_mandate_sale/i18n/nl.po
odoo/addons/account_payment_mandate_sale/i18n/nl_NL.po
odoo/addons/account_payment_mandate_sale/i18n/pt_BR.po
odoo/addons/account_payment_mandate_sale/i18n/sl.po
odoo/addons/account_payment_mandate_sale/models/__init__.py
odoo/addons/account_payment_mandate_sale/models/sale_order.py
odoo/addons/account_payment_mandate_sale/readme/CONFIGURATION.rst
odoo/addons/account_payment_mandate_sale/readme/CONTRIBUTORS.md
odoo/addons/account_payment_mandate_sale/readme/DESCRIPTION.md
odoo/addons/account_payment_mandate_sale/readme/USAGE.md
odoo/addons/account_payment_mandate_sale/static/description/icon.png
odoo/addons/account_payment_mandate_sale/static/description/index.html
odoo/addons/account_payment_mandate_sale/views/sale_order.xml
odoo_addon_account_payment_mandate_sale-19.0.1.0.0.2.dist-info/METADATA
odoo_addon_account_payment_mandate_sale-19.0.1.0.0.2.dist-info/WHEEL
odoo_addon_account_payment_mandate_sale-19.0.1.0.0.2.dist-info/top_level.txt
odoo_addon_account_payment_mandate_sale-19.0.1.0.0.2.dist-info/RECORD
