Metadata-Version: 2.1
Name: odoo-addon-account_payment_mandate_sale
Version: 19.0.1.0.0.2
Requires-Dist: odoo-addon-account_payment_base_oca_sale==19.0.*
Requires-Dist: odoo-addon-account_payment_mandate==19.0.*
Requires-Dist: odoo==19.0.*
Summary: Adds mandates on sale orders
Home-page: https://github.com/OCA/bank-payment-alternative
License: AGPL-3
Author: Odoo Community Association (OCA), Akretion
Author-email: support@odoo-community.org
Classifier: Programming Language :: Python
Classifier: Framework :: Odoo
Classifier: Framework :: Odoo :: 19.0
Classifier: License :: OSI Approved :: GNU Affero General Public License v3
